[
  {
    "synchronous": false,
    "frequency": 1,
    "length": 46,
    "target_ratio": 0.9,
    "generated_ratio": 0.43478260869565216,
    "states": [
      "1001101",
      "1001101",
      "1011101",
      "1111101",
      "0111101",
      "0111111",
      "0111111",
      "0111111",
      "0111111",
      "0111111",
      "0011111",
      "0011111",
      "0011111",
      "0011111",
      "0011111",
      "0011110",
      "0001110",
      "0001110",
      "0001110",
      "1001110",
      "1000110",
      "1000110",
      "1000110",
      "1000110",
      "1000110",
      "1000110",
      "1000110",
      "1000110",
      "1000110",
      "1000110",
      "1000110",
      "1000110",
      "1000110",
      "1000110",
      "1000110",
      "1000110",
      "1000110",
      "1000110",
      "1000110",
      "1000110",
      "1000110",
      "1000110",
      "1000110",
      "1000110",
      "1000110",
      "1000110"
    ]
  },
  {
    "synchronous": false,
    "frequency": 1,
    "length": 16,
    "target_ratio": 0.9,
    "generated_ratio": 0.25,
    "states": [
      "0010010",
      "0010010",
      "1010010",
      "1010110",
      "1000110",
      "1000110",
      "1000110",
      "1000110",
      "1000110",
      "1000110",
      "1000110",
      "1000110",
      "1000110",
      "1000110",
      "1000110",
      "1000110"
    ]
  },
  {
    "synchronous": false,
    "frequency": 1,
    "length": 27,
    "target_ratio": 0.9,
    "generated_ratio": 0.37037037037037035,
    "states": [
      "0010101",
      "0010101",
      "0010101",
      "0010100",
      "0010100",
      "1010100",
      "1010110",
      "1010110",
      "1010110",
      "1010110",
      "1000110",
      "1000110",
      "1000110",
      "1000110",
      "1000110",
      "1000110",
      "1000110",
      "1000110",
      "1000110",
      "1000110",
      "1000110",
      "1000110",
      "1000110",
      "1000110",
      "1000110",
      "1000110",
      "1000110"
    ]
  },
  {
    "synchronous": false,
    "frequency": 1,
    "length": 12,
    "target_ratio": 0.9,
    "generated_ratio": 0.4166666666666667,
    "states": [
      "1100111",
      "1100111",
      "1101111",
      "1001111",
      "1001110",
      "1000110",
      "1000110",
      "1000110",
      "1000110",
      "1000110",
      "1000110",
      "1000110"
    ]
  },
  {
    "synchronous": false,
    "frequency": 1,
    "length": 18,
    "target_ratio": 0.9,
    "generated_ratio": 0.4444444444444444,
    "states": [
      "1011111",
      "1011111",
      "1011110",
      "1011110",
      "1001110",
      "1001110",
      "1001110",
      "1001110",
      "1000110",
      "1000110",
      "1000110",
      "1000110",
      "1000110",
      "1000110",
      "1000110",
      "1000110",
      "1000110",
      "1000110"
    ]
  },
  {
    "synchronous": false,
    "frequency": 1,
    "length": 26,
    "target_ratio": 0.9,
    "generated_ratio": 0.07692307692307693,
    "states": [
      "1010110",
      "1010110",
      "1000110",
      "1000110",
      "1000110",
      "1000110",
      "1000110",
      "1000110",
      "1000110",
      "1000110",
      "1000110",
      "1000110",
      "1000110",
      "1000110",
      "1000110",
      "1000110",
      "1000110",
      "1000110",
      "1000110",
      "1000110",
      "1000110",
      "1000110",
      "1000110",
      "1000110",
      "1000110",
      "1000110"
    ]
  },
  {
    "synchronous": false,
    "frequency": 1,
    "length": 26,
    "target_ratio": 0.9,
    "generated_ratio": 0.7307692307692307,
    "states": [
      "1100001",
      "1100001",
      "1100101",
      "1100100",
      "1101100",
      "1101110",
      "1101111",
      "1101111",
      "1001111",
      "1001110",
      "1001110",
      "1001110",
      "1001110",
      "1001110",
      "1001110",
      "1001110",
      "1001110",
      "1001110",
      "1001110",
      "1000110",
      "1000110",
      "1000110",
      "1000110",
      "1000110",
      "1000110",
      "1000110"
    ]
  },
  {
    "synchronous": false,
    "frequency": 1,
    "length": 31,
    "target_ratio": 0.9,
    "generated_ratio": 0.45161290322580644,
    "states": [
      "1110010",
      "1110010",
      "1110011",
      "1111011",
      "0111011",
      "0011011",
      "0011011",
      "0011011",
      "0011010",
      "1011010",
      "1011010",
      "1010010",
      "1010110",
      "1010110",
      "1000110",
      "1000110",
      "1000110",
      "1000110",
      "1000110",
      "1000110",
      "1000110",
      "1000110",
      "1000110",
      "1000110",
      "1000110",
      "1000110",
      "1000110",
      "1000110",
      "1000110",
      "1000110",
      "1000110"
    ]
  },
  {
    "synchronous": false,
    "frequency": 1,
    "length": 46,
    "target_ratio": 0.9,
    "generated_ratio": 0.17391304347826086,
    "states": [
      "1101101",
      "1101101",
      "1101100",
      "1101100",
      "1101100",
      "1101100",
      "1101110",
      "1001110",
      "1000110",
      "1000110",
      "1000110",
      "1000110",
      "1000110",
      "1000110",
      "1000110",
      "1000110",
      "1000110",
      "1000110",
      "1000110",
      "1000110",
      "1000110",
      "1000110",
      "1000110",
      "1000110",
      "1000110",
      "1000110",
      "1000110",
      "1000110",
      "1000110",
      "1000110",
      "1000110",
      "1000110",
      "1000110",
      "1000110",
      "1000110",
      "1000110",
      "1000110",
      "1000110",
      "1000110",
      "1000110",
      "1000110",
      "1000110",
      "1000110",
      "1000110",
      "1000110",
      "1000110"
    ]
  },
  {
    "synchronous": false,
    "frequency": 1,
    "length": 43,
    "target_ratio": 0.9,
    "generated_ratio": 0.23255813953488372,
    "states": [
      "0111001",
      "0111001",
      "0111011",
      "0011011",
      "0011011",
      "0011010",
      "0011110",
      "1011110",
      "1001110",
      "1001110",
      "1000110",
      "1000110",
      "1000110",
      "1000110",
      "1000110",
      "1000110",
      "1000110",
      "1000110",
      "1000110",
      "1000110",
      "1000110",
      "1000110",
      "1000110",
      "1000110",
      "1000110",
      "1000110",
      "1000110",
      "1000110",
      "1000110",
      "1000110",
      "1000110",
      "1000110",
      "1000110",
      "1000110",
      "1000110",
      "1000110",
      "1000110",
      "1000110",
      "1000110",
      "1000110",
      "1000110",
      "1000110",
      "1000110"
    ]
  },
  {
    "synchronous": false,
    "frequency": 1,
    "length": 31,
    "target_ratio": 0.9,
    "generated_ratio": 0.3225806451612903,
    "states": [
      "0010111",
      "0010111",
      "0010111",
      "0010110",
      "0011110",
      "0011110",
      "0011110",
      "0001110",
      "0001110",
      "1001110",
      "1000110",
      "1000110",
      "1000110",
      "1000110",
      "1000110",
      "1000110",
      "1000110",
      "1000110",
      "1000110",
      "1000110",
      "1000110",
      "1000110",
      "1000110",
      "1000110",
      "1000110",
      "1000110",
      "1000110",
      "1000110",
      "1000110",
      "1000110",
      "1000110"
    ]
  },
  {
    "synchronous": false,
    "frequency": 1,
    "length": 16,
    "target_ratio": 0.9,
    "generated_ratio": 0.3125,
    "states": [
      "0101111",
      "0101111",
      "1101111",
      "1001111",
      "1001110",
      "1000110",
      "1000110",
      "1000110",
      "1000110",
      "1000110",
      "1000110",
      "1000110",
      "1000110",
      "1000110",
      "1000110",
      "1000110"
    ]
  },
  {
    "synchronous": false,
    "frequency": 1,
    "length": 11,
    "target_ratio": 0.9,
    "generated_ratio": 0.9090909090909091,
    "states": [
      "0010100",
      "0110100",
      "1110100",
      "1110110",
      "1010110",
      "1010110",
      "1010110",
      "1010110",
      "1010110",
      "1010110",
      "1000110"
    ]
  },
  {
    "synchronous": false,
    "frequency": 1,
    "length": 38,
    "target_ratio": 0.9,
    "generated_ratio": 0.23684210526315788,
    "states": [
      "1011000",
      "1011000",
      "1001000",
      "1101000",
      "1101010",
      "1101010",
      "1001010",
      "1001010",
      "1000010",
      "1000110",
      "1000110",
      "1000110",
      "1000110",
      "1000110",
      "1000110",
      "1000110",
      "1000110",
      "1000110",
      "1000110",
      "1000110",
      "1000110",
      "1000110",
      "1000110",
      "1000110",
      "1000110",
      "1000110",
      "1000110",
      "1000110",
      "1000110",
      "1000110",
      "1000110",
      "1000110",
      "1000110",
      "1000110",
      "1000110",
      "1000110",
      "1000110",
      "1000110"
    ]
  },
  {
    "synchronous": false,
    "frequency": 1,
    "length": 49,
    "target_ratio": 0.9,
    "generated_ratio": 0.04081632653061224,
    "states": [
      "1001110",
      "1001110",
      "1000110",
      "1000110",
      "1000110",
      "1000110",
      "1000110",
      "1000110",
      "1000110",
      "1000110",
      "1000110",
      "1000110",
      "1000110",
      "1000110",
      "1000110",
      "1000110",
      "1000110",
      "1000110",
      "1000110",
      "1000110",
      "1000110",
      "1000110",
      "1000110",
      "1000110",
      "1000110",
      "1000110",
      "1000110",
      "1000110",
      "1000110",
      "1000110",
      "1000110",
      "1000110",
      "1000110",
      "1000110",
      "1000110",
      "1000110",
      "1000110",
      "1000110",
      "1000110",
      "1000110",
      "1000110",
      "1000110",
      "1000110",
      "1000110",
      "1000110",
      "1000110",
      "1000110",
      "1000110",
      "1000110"
    ]
  },
  {
    "synchronous": false,
    "frequency": 1,
    "length": 42,
    "target_ratio": 0.9,
    "generated_ratio": 0.16666666666666666,
    "states": [
      "0100100",
      "0100100",
      "0100100",
      "0100110",
      "0110110",
      "1110110",
      "1010110",
      "1000110",
      "1000110",
      "1000110",
      "1000110",
      "1000110",
      "1000110",
      "1000110",
      "1000110",
      "1000110",
      "1000110",
      "1000110",
      "1000110",
      "1000110",
      "1000110",
      "1000110",
      "1000110",
      "1000110",
      "1000110",
      "1000110",
      "1000110",
      "1000110",
      "1000110",
      "1000110",
      "1000110",
      "1000110",
      "1000110",
      "1000110",
      "1000110",
      "1000110",
      "1000110",
      "1000110",
      "1000110",
      "1000110",
      "1000110",
      "1000110"
    ]
  },
  {
    "synchronous": false,
    "frequency": 1,
    "length": 43,
    "target_ratio": 0.9,
    "generated_ratio": 0.23255813953488372,
    "states": [
      "1000100",
      "1000100",
      "1000100",
      "1100100",
      "1110100",
      "1111100",
      "1111100",
      "1101100",
      "1101110",
      "1001110",
      "1000110",
      "1000110",
      "1000110",
      "1000110",
      "1000110",
      "1000110",
      "1000110",
      "1000110",
      "1000110",
      "1000110",
      "1000110",
      "1000110",
      "1000110",
      "1000110",
      "1000110",
      "1000110",
      "1000110",
      "1000110",
      "1000110",
      "1000110",
      "1000110",
      "1000110",
      "1000110",
      "1000110",
      "1000110",
      "1000110",
      "1000110",
      "1000110",
      "1000110",
      "1000110",
      "1000110",
      "1000110",
      "1000110"
    ]
  },
  {
    "synchronous": false,
    "frequency": 1,
    "length": 34,
    "target_ratio": 0.9,
    "generated_ratio": 0.38235294117647056,
    "states": [
      "1100001",
      "1100001",
      "1100000",
      "1101000",
      "1101000",
      "1101010",
      "1101110",
      "1101110",
      "1101110",
      "1101110",
      "1101111",
      "1001111",
      "1001110",
      "1000110",
      "1000110",
      "1000110",
      "1000110",
      "1000110",
      "1000110",
      "1000110",
      "1000110",
      "1000110",
      "1000110",
      "1000110",
      "1000110",
      "1000110",
      "1000110",
      "1000110",
      "1000110",
      "1000110",
      "1000110",
      "1000110",
      "1000110",
      "1000110"
    ]
  },
  {
    "synchronous": false,
    "frequency": 1,
    "length": 46,
    "target_ratio": 0.9,
    "generated_ratio": 0.21739130434782608,
    "states": [
      "0111100",
      "0111100",
      "0111110",
      "0101110",
      "0001110",
      "0001110",
      "0001110",
      "0001110",
      "0001110",
      "1001110",
      "1000110",
      "1000110",
      "1000110",
      "1000110",
      "1000110",
      "1000110",
      "1000110",
      "1000110",
      "1000110",
      "1000110",
      "1000110",
      "1000110",
      "1000110",
      "1000110",
      "1000110",
      "1000110",
      "1000110",
      "1000110",
      "1000110",
      "1000110",
      "1000110",
      "1000110",
      "1000110",
      "1000110",
      "1000110",
      "1000110",
      "1000110",
      "1000110",
      "1000110",
      "1000110",
      "1000110",
      "1000110",
      "1000110",
      "1000110",
      "1000110",
      "1000110"
    ]
  },
  {
    "synchronous": false,
    "frequency": 1,
    "length": 26,
    "target_ratio": 0.9,
    "generated_ratio": 0.5769230769230769,
    "states": [
      "0001111",
      "0001111",
      "0001111",
      "0011111",
      "0011111",
      "0011111",
      "0011111",
      "0011111",
      "0011110",
      "0001110",
      "1001110",
      "1001110",
      "1001110",
      "1001110",
      "1001110",
      "1000110",
      "1000110",
      "1000110",
      "1000110",
      "1000110",
      "1000110",
      "1000110",
      "1000110",
      "1000110",
      "1000110",
      "1000110"
    ]
  },
  {
    "synchronous": false,
    "frequency": 1,
    "length": 28,
    "target_ratio": 0.9,
    "generated_ratio": 0.17857142857142858,
    "states": [
      "0000111",
      "0000111",
      "1000111",
      "1001111",
      "1001110",
      "1000110",
      "1000110",
      "1000110",
      "1000110",
      "1000110",
      "1000110",
      "1000110",
      "1000110",
      "1000110",
      "1000110",
      "1000110",
      "1000110",
      "1000110",
      "1000110",
      "1000110",
      "1000110",
      "1000110",
      "1000110",
      "1000110",
      "1000110",
      "1000110",
      "1000110",
      "1000110"
    ]
  },
  {
    "synchronous": false,
    "frequency": 1,
    "length": 17,
    "target_ratio": 0.9,
    "generated_ratio": 0.5294117647058824,
    "states": [
      "0100100",
      "0100100",
      "1100100",
      "1100100",
      "1101100",
      "1101100",
      "1101110",
      "1001110",
      "1001110",
      "1000110",
      "1000110",
      "1000110",
      "1000110",
      "1000110",
      "1000110",
      "1000110",
      "1000110"
    ]
  },
  {
    "synchronous": false,
    "frequency": 1,
    "length": 35,
    "target_ratio": 0.9,
    "generated_ratio": 0.2857142857142857,
    "states": [
      "1100010",
      "1100010",
      "1110010",
      "1110110",
      "1110110",
      "1111110",
      "1111110",
      "1111110",
      "1101110",
      "1001110",
      "1000110",
      "1000110",
      "1000110",
      "1000110",
      "1000110",
      "1000110",
      "1000110",
      "1000110",
      "1000110",
      "1000110",
      "1000110",
      "1000110",
      "1000110",
      "1000110",
      "1000110",
      "1000110",
      "1000110",
      "1000110",
      "1000110",
      "1000110",
      "1000110",
      "1000110",
      "1000110",
      "1000110",
      "1000110"
    ]
  },
  {
    "synchronous": false,
    "frequency": 1,
    "length": 31,
    "target_ratio": 0.9,
    "generated_ratio": 0.5483870967741935,
    "states": [
      "1000001",
      "1000001",
      "1001001",
      "1101001",
      "1101011",
      "1101111",
      "1101111",
      "1111111",
      "0111111",
      "0011111",
      "0011110",
      "0001110",
      "0001110",
      "0001110",
      "0001110",
      "1001110",
      "1001110",
      "1000110",
      "1000110",
      "1000110",
      "1000110",
      "1000110",
      "1000110",
      "1000110",
      "1000110",
      "1000110",
      "1000110",
      "1000110",
      "1000110",
      "1000110",
      "1000110"
    ]
  },
  {
    "synchronous": false,
    "frequency": 1,
    "length": 17,
    "target_ratio": 0.9,
    "generated_ratio": 0.35294117647058826,
    "states": [
      "0010110",
      "0010110",
      "0011110",
      "0011110",
      "1011110",
      "1010110",
      "1000110",
      "1000110",
      "1000110",
      "1000110",
      "1000110",
      "1000110",
      "1000110",
      "1000110",
      "1000110",
      "1000110",
      "1000110"
    ]
  }
]